baserow/__init__.py
baserow/lib.py
baserow/table.py
baserow/util.py
baserow-0.0.1.dist-info/METADATA
baserow-0.0.1.dist-info/WHEEL
baserow-0.0.1.dist-info/top_level.txt
baserow-0.0.1.dist-info/RECORD
